<?xml version="1.0" encoding="utf-8"?>
<!DOCTYPE hibernate-mapping PUBLIC "-//Hibernate/Hibernate Mapping DTD 3.0//EN"
"http://hibernate.sourceforge.net/hibernate-mapping-3.0.dtd">
<!-- 
    Mapping file autogenerated by MyEclipse Persistence Tools
-->
<hibernate-mapping>
    <class name="com.zs.entity.XtBranches" table="xt_branches" catalog="it_bdm">
        <id name="BId" type="java.lang.String">
            <column name="b_id" />
            <generator class="assigned" />
        </id>
        <property name="BDate" type="java.util.Date">
            <column name="b_date" />
        </property>
        <property name="BMaintainDate" type="java.util.Date">
            <column name="b_maintain_date" length="10" />
        </property>
        <property name="BMaintainWeek" type="java.lang.Integer">
            <column name="b_maintain_week" />
        </property>
        <property name="BNum1" type="java.lang.String">
            <column name="b_num_1" />
        </property>
        <property name="BName1" type="java.lang.String">
            <column name="b_name_1" />
        </property>
        <property name="BMaster1" type="java.lang.String">
            <column name="b_master_1" />
        </property>
        <property name="BPhone1" type="java.lang.String">
            <column name="b_phone_1" />
        </property>
        <property name="BMaster2" type="java.lang.String">
            <column name="b_master_2" />
        </property>
        <property name="BCard2" type="java.lang.String">
            <column name="b_card_2" />
        </property>
        <property name="BPhone2" type="java.lang.String">
            <column name="b_phone_2" />
        </property>
        <property name="BNum2" type="java.lang.String">
            <column name="b_num_2" />
        </property>
        <property name="BName2" type="java.lang.String">
            <column name="b_name_2" />
        </property>
        <property name="BNote" type="java.lang.String">
            <column name="b_note" />
        </property>
    </class>
</hibernate-mapping>
